flex_telegram_bot/__init__.py
flex_telegram_bot-0.2.1.dist-info/METADATA
flex_telegram_bot-0.2.1.dist-info/WHEEL
flex_telegram_bot-0.2.1.dist-info/top_level.txt
flex_telegram_bot-0.2.1.dist-info/RECORD
