Metadata-Version: 2.1
Name: flex-telegram-bot
Version: 0.2.1
Summary: Esnek Türkçe Telegram bot kütüphanesi.
Home-page: UNKNOWN
Author: FlexN01
Author-email: v.flexn01@gmail.com
License: UNKNOWN
Platform: UNKNOWN
Classifier: Programming Language :: Python :: 3
Classifier: License :: OSI Approved :: MIT License
Classifier: Operating System :: OS Independent
Requires-Python: >=3.6
Requires-Dist: requests
